akto_gateway/__init__.py
akto_gateway/__main__.py
akto_gateway/api_client.py
akto_gateway/constants.py
akto_gateway/device_utils.py
akto_gateway/ingest_utils.py
akto_gateway/logger.py
akto_gateway/session.py
akto_gateway/transport.py
mcp_wrapper-0.1.0.dist-info/METADATA
mcp_wrapper-0.1.0.dist-info/WHEEL
mcp_wrapper-0.1.0.dist-info/entry_points.txt
mcp_wrapper-0.1.0.dist-info/top_level.txt
mcp_wrapper-0.1.0.dist-info/RECORD
