Metadata-Version: 2.4
Name: mcp-wrapper
Version: 0.1.0
Summary: Akto MCP wrapper for threat detection and discovery
Author: Akto Team
Requires-Python: >=3.6
Requires-Dist: aiohttp>=3.8.0
Requires-Dist: py-machineid>=0.5.0
